{
  "asset_name": "aip.encrypted.s3",
  "asset_id": "f97b25055b63cfbf3bc0",
  "run_group_id": "4b677faf52f7aa0c01c0",
  "active": true,
  "tasks": [
    {
      "task_id": "eb75e10bbd1ab4f39d04",
      "asset_id": "f97b25055b63cfbf3bc0",
      "seq_number": 0,
      "description": null,
      "type": "encrypt",
      "active": true,
      "source": null,
      "target": {
        "path": "aip/",
        "type": "encrypt",
        "active": true,
        "filename": "CityofAsheville5871_To_InfoArmor_FULL_${YYYY}${MM}${DD}.txt",
        "s3_connection": "s3_data_files",
        "encrypt_connection": "aip_ftp",
        "encrypted_filename": "CityofAsheville5871_To_InfoArmor_FULL_${YYYY}${MM}${DD}"
      },
      "configuration": null
    }
  ]
}